pysysair/__init__.py
pysysair/auth.py
pysysair/client.py
pysysair/consts.py
pysysair/graphql/__init__.py
pysysair/graphql/async_base_client.py
pysysair/graphql/base_model.py
pysysair/graphql/client.py
pysysair/graphql/enums.py
pysysair/graphql/exceptions.py
pysysair/graphql/get_all_devices.py
pysysair/graphql/input_types.py
pysysair-0.1.0.dist-info/LICENSE
pysysair-0.1.0.dist-info/METADATA
pysysair-0.1.0.dist-info/WHEEL
pysysair-0.1.0.dist-info/RECORD
