Metadata-Version: 2.1
Name: pysysair
Version: 0.1.0
Summary: Systemair API Bindings for Python
License: MIT
Author: Robert W
Author-email: 1263192+rbw@users.noreply.github.com
Requires-Python: >=3.11,<4.0
Classifier: License :: OSI Approved :: MIT License
Classifier: Programming Language :: Python :: 3
Classifier: Programming Language :: Python :: 3.11
Classifier: Programming Language :: Python :: 3.12
Requires-Dist: httpx (>=0.26.0,<0.27.0)
Requires-Dist: pydantic (>=2.6.1,<3.0.0)
